LICENSE
MANIFEST.in
README.rst
setup.cfg
setup.py
Flask_LinkTester.egg-info/PKG-INFO
Flask_LinkTester.egg-info/SOURCES.txt
Flask_LinkTester.egg-info/dependency_links.txt
Flask_LinkTester.egg-info/not-zip-safe
Flask_LinkTester.egg-info/requires.txt
Flask_LinkTester.egg-info/top_level.txt
docs/Makefile
docs/conf.py
docs/index.rst
docs/make.bat
docs/_static/flask-testing.png
docs/_themes/LICENSE
docs/_themes/README
docs/_themes/flask_theme_support.py
docs/_themes/flask_small/layout.html
docs/_themes/flask_small/theme.conf
docs/_themes/flask_small/static/flasky.css_t
flask_linktester/__init__.py
flask_linktester/linktester.py
tests/__init__.py
tests/dummy_app.py
tests/test_linktester.py