Metadata-Version: 1.1
Name: Flask-LinkTester
Version: 0.3.0
Summary: Link tester for Flask applications
Home-page: http://github.com/sfermigier/flask-linktester
Author: Stefane Fermigier
Author-email: sf@fermigier.com
License: BSD
Platform: any
Classifier: Development Status :: 4 - Beta
Classifier: Environment :: Web Environment
Classifier: Intended Audience :: Developers
Classifier: License :: OSI Approved :: BSD License
Classifier: Operating System :: OS Independent
Classifier: Programming Language :: Python
Classifier: Topic :: Internet :: WWW/HTTP :: Dynamic Content
Classifier: Topic :: Software Development :: Libraries :: Python Modules
